qtrack/__init__.py
qtrack/core.py
qtrack/curvvort.py
qtrack/nondivwind.py
qtrack/tracking.py
qtrack-0.0.4.dist-info/LICENSE
qtrack-0.0.4.dist-info/WHEEL
qtrack-0.0.4.dist-info/METADATA
qtrack-0.0.4.dist-info/RECORD
