Metadata-Version: 2.1
Name: qtrack
Version: 0.0.4
Summary: QTrack - African Easterly Wave Tracking in Model and Reanalysis Data
Author-email: qlawton <qlawton@ucar.edu>
Requires-Python: ~=3.8
Classifier: License :: OSI Approved :: MIT License
Requires-Dist: Cartopy
Requires-Dist: dill
Requires-Dist: imageio
Requires-Dist: joblib
Requires-Dist: matplotlib
Requires-Dist: netCDF4
Requires-Dist: numpy
Requires-Dist: pandas
Requires-Dist: scikit-learn
Requires-Dist: scipy
Requires-Dist: tropycal
Requires-Dist: xarray
Requires-Dist: gdown ; extra == "test"
Requires-Dist: pytest ; extra == "test"
Project-URL: Home, https://github.com/qlawton/QTrack
Provides-Extra: test
